lontras/__about__.py
lontras/__init__.py
lontras/lontras.py
lontras-0.0.2.dist-info/METADATA
lontras-0.0.2.dist-info/WHEEL
lontras-0.0.2.dist-info/licenses/LICENSE.txt
lontras-0.0.2.dist-info/RECORD
