Metadata-Version: 2.4
Name: lontras
Version: 0.0.2
Summary: A lightweight, dictionary-based DataFrame implementation in pure Python. Designed for simplicity and ease of use. Perfect for small projects or when a full-fledged DataFrame library is overkill.
Project-URL: Documentation, https://github.com/Luiz Eduardo Amaral/lontras#readme
Project-URL: Issues, https://github.com/Luiz Eduardo Amaral/lontras/issues
Project-URL: Source, https://github.com/Luiz Eduardo Amaral/lontras
Author-email: Luiz Eduardo Amaral <luizamaral306@gmail.com>
License-Expression: MIT
License-File: LICENSE.txt
Keywords: dataframe
Classifier: Development Status :: 4 - Beta
Classifier: Intended Audience :: Science/Research
Classifier: License :: OSI Approved :: MIT License
Classifier: Operating System :: OS Independent
Classifier: Programming Language :: Python
Classifier: Programming Language :: Python :: 3.11
Classifier: Programming Language :: Python :: 3.12
Classifier: Programming Language :: Python :: 3.13
Classifier: Programming Language :: Python :: Implementation :: CPython
Classifier: Programming Language :: Python :: Implementation :: PyPy
Classifier: Topic :: Scientific/Engineering
Requires-Python: >=3.8
Provides-Extra: dev
Requires-Dist: pandas; extra == 'dev'
